sensifai/__init__.py
sensifai/rest.py
sensifai-0.1.2.dist-info/METADATA
sensifai-0.1.2.dist-info/RECORD
sensifai-0.1.2.dist-info/WHEEL
sensifai-0.1.2.dist-info/top_level.txt
