Metadata-Version: 2.1
Name: sensifai
Version: 0.1.2
Summary: Sensifai API Python Client
Home-page: https://github.com/sensifai/sensifai_python
Author-email: api@sensifai.com
Maintainer: Rahman yousefzadeh
Maintainer-email: r.y.zadeh@Sensifai.com
License: apache-2.0
Keywords: Sensofai; Video Recognition;
Platform: UNKNOWN
Classifier: Development Status :: 4 - Beta
Classifier: Intended Audience :: Developers
Classifier: Topic :: Software Development :: Build Tools
Classifier: Topic :: Multimedia :: Video
Classifier: License :: OSI Approved :: Apache Software License
Requires-Python: >=3
Provides-Extra: reST
Provides-Extra: reST
Requires-Dist: Docutils (>=0.14); extra == 'reST'
